giger/__init__.py
giger/cli.py
giger/commands/image.py
giger/commands/prompt.py
giger/commands/swap.py
giger/commands/upscale.py
giger/services/image.py
giger/services/prompt.py
giger/services/swap.py
giger/services/upscale.py
giger-0.3.4.dist-info/LICENSE.txt
giger-0.3.4.dist-info/METADATA
giger-0.3.4.dist-info/WHEEL
giger-0.3.4.dist-info/entry_points.txt
giger-0.3.4.dist-info/top_level.txt
giger-0.3.4.dist-info/RECORD
