Metadata-Version: 2.1
Name: giger
Version: 0.3.4
Summary: CLI for Stable Diffusion tasks.
Home-page: https://github.com/artificialhoney/giger/
Author: Sebastian Krüger
Author-email: sk@honeymachine.io
License: MIT
Project-URL: Documentation, https://artificialhoney.github.io/giger/
Project-URL: Source, https://github.com/artificialhoney/giger/
Project-URL: Tracker, https://github.com/artificialhoney/giger/issues
Project-URL: Download, https://pypi.org/project/giger/#files
Platform: any
Classifier: Development Status :: 4 - Beta
Classifier: Programming Language :: Python
License-File: LICENSE.txt
Requires-Dist: transformers
Requires-Dist: jinja2
Requires-Dist: pyyaml
Requires-Dist: diffusers
Requires-Dist: peft
Requires-Dist: absl-py
Requires-Dist: astunparse
Requires-Dist: array-record
Requires-Dist: torch
Requires-Dist: torchvision
Requires-Dist: piexif
Requires-Dist: accelerate
Requires-Dist: xformers
Requires-Dist: safetensors
Requires-Dist: insightface
Requires-Dist: onnx
Requires-Dist: onnxruntime
Requires-Dist: huggingface-hub
Requires-Dist: numpy
Requires-Dist: gfpgan
Requires-Dist: triton
Requires-Dist: importlib-metadata ; python_version < "3.8"
Provides-Extra: testing
Requires-Dist: setuptools ; extra == 'testing'
Requires-Dist: pytest ; extra == 'testing'
Requires-Dist: pytest-cov ; extra == 'testing'
